Metadata-Version: 2.1
Name: pou-shap
Version: 0.41.0
Summary: A unified approach to explain the output of any machine learning model.
Author-email: Scott Lundberg <slund1@cs.washington.edu>
License: MIT License
Project-URL: Repository, http://github.com/slundberg/shap
Project-URL: Documentation, https://shap.readthedocs.io/en/latest/index.html
Classifier: Operating System :: Microsoft :: Windows
Classifier: Operating System :: POSIX
Classifier: Operating System :: Unix
Classifier: Operating System :: MacOS
Classifier: Programming Language :: Python :: 3.7
Classifier: Programming Language :: Python :: 3.8
Classifier: Programming Language :: Python :: 3.9
Classifier: Programming Language :: Python :: 3.10
Classifier: Programming Language :: Python :: 3.11
Requires-Python: >=3.7
License-File: LICENSE
Requires-Dist: numpy (==1.24.4)
Requires-Dist: scipy (==1.11.0)
Requires-Dist: scikit-learn (==1.2.2)
Requires-Dist: pandas (==2.0.2)
Requires-Dist: tqdm (>=4.27.0)
Requires-Dist: packaging (>20.9)
Requires-Dist: slicer (==0.0.7)
Requires-Dist: numba (==0.57.1)
Requires-Dist: cloudpickle (==2.2.1)
Provides-Extra: docs
Requires-Dist: matplotlib ; extra == 'docs'
Requires-Dist: ipython ; extra == 'docs'
Requires-Dist: numpydoc ; extra == 'docs'
Requires-Dist: sphinx-rtd-theme ; extra == 'docs'
Requires-Dist: sphinx ; extra == 'docs'
Requires-Dist: nbsphinx ; extra == 'docs'
Provides-Extra: others
Requires-Dist: lime ; extra == 'others'
Provides-Extra: plots
Requires-Dist: matplotlib ; extra == 'plots'
Requires-Dist: ipython ; extra == 'plots'
Provides-Extra: test
Requires-Dist: pytest ; extra == 'test'
Requires-Dist: pytest-mpl ; extra == 'test'
Requires-Dist: pytest-cov ; extra == 'test'
Requires-Dist: xgboost ; extra == 'test'
Requires-Dist: lightgbm ; extra == 'test'
Requires-Dist: catboost ; extra == 'test'
Requires-Dist: pyspark ; extra == 'test'
Requires-Dist: pyod ; extra == 'test'
Requires-Dist: transformers ; extra == 'test'
Requires-Dist: torch ; extra == 'test'
Requires-Dist: torchvision ; extra == 'test'
Requires-Dist: tensorflow ; extra == 'test'
Requires-Dist: sentencepiece ; extra == 'test'
Requires-Dist: opencv-python ; extra == 'test'
Provides-Extra: test-core
Requires-Dist: pytest ; extra == 'test-core'
Requires-Dist: pytest-mpl ; extra == 'test-core'
Requires-Dist: pytest-cov ; extra == 'test-core'
